gower/__init__.py
gower/gower_dist.py
gower-0.1.1.dist-info/LICENSE
gower-0.1.1.dist-info/METADATA
gower-0.1.1.dist-info/WHEEL
gower-0.1.1.dist-info/top_level.txt
gower-0.1.1.dist-info/RECORD
