Metadata-Version: 2.1
Name: gower
Version: 0.1.1
Summary: Python implementation of Gowers distance, pairwise between records in two data sets
Home-page: https://github.com/wwwjk366/gower
Author: Dominic D
Author-email: Michael Yan <author@example.com>
License: MIT
Project-URL: Homepage, https://github.com/wwwjk366/gower
Keywords: gower,distance,matrix
Classifier: Programming Language :: Python :: 3
Classifier: License :: OSI Approved :: MIT License
Classifier: Operating System :: OS Independent
Requires-Python: >=2.7
License-File: LICENSE
Requires-Dist: numpy
Requires-Dist: scipy
